LICENSE
MANIFEST.in
Makefile
README.md
requirements.txt
requirements_dev.txt
setup.py
SimilarWeb_Python.egg-info/PKG-INFO
SimilarWeb_Python.egg-info/SOURCES.txt
SimilarWeb_Python.egg-info/dependency_links.txt
SimilarWeb_Python.egg-info/requires.txt
SimilarWeb_Python.egg-info/top_level.txt
similarweb/__init__.py
similarweb/base.py
similarweb/exceptions.py
similarweb/utils.py