Metadata-Version: 1.1
Name: SimilarWeb-Python
Version: 0.0.3
Summary: Python Wrapper for SimilarWeb API
Home-page: https://github.com/audiencepi/SimilarWeb-Python
Author: Ryan Liao
Author-email: pirsquare.ryan@gmail.com
License: MIT
Platform: UNKNOWN
Classifier: Development Status :: 4 - Beta
Classifier: Environment :: Web Environment
Classifier: Intended Audience :: Developers
Classifier: Operating System :: OS Independent
Classifier: Programming Language :: Python
